<?xml version="1.0" encoding="UTF-8"?>
<Variant ID="edeeaefc-f348-48b9-a810-89885eca5c64">
  <Name>Neue Entwurfsvariante</Name>
  <Zone>
    <LocationX unit="m">0</LocationX>
    <LocationY unit="m">0</LocationY>
    <Width unit="mm">500.0</Width>
    <Height unit="mm">250.0</Height>
    <StoneDamages>
      <Stone ID="17OghfDpT3z8TA46unsHcr">17OghfDpT3z8TA46unsHcr</Stone>
      <Stone ID="2y1C0yiQ14UB2xm0MQIBfX">2y1C0yiQ14UB2xm0MQIBfX</Stone>
      <Stone ID="3fp69Ca2L51REoBEcYBNsN">3fp69Ca2L51REoBEcYBNsN</Stone>
      <Stone ID="17OghfDpT3z8TA46unsHcr">17OghfDpT3z8TA46unsHcr</Stone>
      <Stone ID="2ZlxvJPlz2GQNcAo_7A38Y">2ZlxvJPlz2GQNcAo_7A38Y</Stone>
      <Stone ID="2rGI_WuF1DJOEzHTPZimnP">2rGI_WuF1DJOEzHTPZimnP</Stone>
      <Stone ID="0ls8Y23X1AOOG7F6HoidjI">0ls8Y23X1AOOG7F6HoidjI</Stone>
      <Stone ID="2P3AVJPg94Mf5PqkqKQ$W9">2P3AVJPg94Mf5PqkqKQ$W9</Stone>
      <Stone ID="3ZlDFXJGTD1xLyYGfmQeUG">3ZlDFXJGTD1xLyYGfmQeUG</Stone>
      <Stone ID="1P5bOr4znBTeNY8iwC3c_I">1P5bOr4znBTeNY8iwC3c_I</Stone>
      <Stone ID="1SV2hX1q14zxWdOBhYyBlY">1SV2hX1q14zxWdOBhYyBlY</Stone>
      <Stone ID="36VlODqb1CFQR_Ph6rpqp0">36VlODqb1CFQR_Ph6rpqp0</Stone>
      <Stone ID="21b4iVKJn5WvWmhtpRKiVJ">21b4iVKJn5WvWmhtpRKiVJ</Stone>
    </StoneDamages>
  </Zone>
  <DamageTypes>
    <DamageType ID="Fracture">Fracture</DamageType>
    <DamageType ID="SingleCrack">SingleCrack</DamageType>
    <DamageType ID="SingleCrack">SingleCrack</DamageType>
    <DamageType ID="Lichen">Lichen</DamageType>
    <DamageType ID="Splitting">Splitting</DamageType>
    <DamageType ID="Craquele">Craquele</DamageType>
    <DamageType ID="SingleCrack">SingleCrack</DamageType>
    <DamageType ID="SingleCrack">SingleCrack</DamageType>
    <DamageType ID="Moss">Moss</DamageType>
  </DamageTypes>
  <RehabilitationMeasures>
    <RehabMeasure ID="preven000">Praeventive Massnahmen</RehabMeasure>
    <RehabMeasure ID="other_plastering000">Neuputz</RehabMeasure>
    <RehabMeasure ID="cleaning000">Reinigung</RehabMeasure>
    <RehabMeasure ID="clean_chem000">Chemische Abnahme</RehabMeasure>
    <RehabMeasure ID="clean_biozide000">Biozide Behandlung</RehabMeasure>
    <RehabMeasure ID="clean_flame000">Abflammen</RehabMeasure>
    <RehabMeasure ID="clean_mech000">Mechanische Abnahme</RehabMeasure>
    <RehabMeasure ID="clean_wet000">Nassreinigung</RehabMeasure>
    <RehabMeasure ID="clean_dry000">Trockenreinigung</RehabMeasure>
    <RehabMeasure ID="securing000">Sicherungsmassnahmen</RehabMeasure>
    <RehabMeasure ID="securing_non_stat_const000">Nicht Statisch-Konstruktive Maßnahmen</RehabMeasure>
    <RehabMeasure ID="securing_crack_filling000">Rissverfuellung</RehabMeasure>
    <RehabMeasure ID="securing_stat_const000">Statisch-Konstruktive Maßnahmen</RehabMeasure>
    <RehabMeasure ID="securing_anchor000">Verankern</RehabMeasure>
    <RehabMeasure ID="securing_needling000">Vernadeln</RehabMeasure>
    <RehabMeasure ID="securing_brace000">Verklammern</RehabMeasure>
    <RehabMeasure ID="securing_pressing000">Verpressen</RehabMeasure>
    <RehabMeasure ID="stone_complement000">Steinergaenzung</RehabMeasure>
  </RehabilitationMeasures>
  <Cost currency="EUR">-</Cost>
  <Duration unit="Tage">1</Duration> 
  <Risk eval="Hoch"/>
  <Evaluation>-</Evaluation> 
</Variant>

